.gitignore
CHANGES.txt
CONTRIBUTORS.txt
MANIFEST.in
README.rst
setup.py
docs/LICENSE.GPL
docs/LICENSE.txt
src/raptus/__init__.py
src/raptus.backgroundsize.egg-info/PKG-INFO
src/raptus.backgroundsize.egg-info/SOURCES.txt
src/raptus.backgroundsize.egg-info/dependency_links.txt
src/raptus.backgroundsize.egg-info/entry_points.txt
src/raptus.backgroundsize.egg-info/namespace_packages.txt
src/raptus.backgroundsize.egg-info/not-zip-safe
src/raptus.backgroundsize.egg-info/requires.txt
src/raptus.backgroundsize.egg-info/top_level.txt
src/raptus/backgroundsize/__init__.py
src/raptus/backgroundsize/configure.zcml
src/raptus/backgroundsize/profiles/default/jsregistry.xml
src/raptus/backgroundsize/profiles/default/metadata.xml
src/raptus/backgroundsize/profiles/default/propertiestool.xml
src/raptus/backgroundsize/profiles/default/skins.xml
src/raptus/backgroundsize/skins/raptus_backgroundsize/backgroundsize.js.py