Metadata-Version: 1.1
Name: raptus.backgroundsize
Version: 1.0a1
Summary: Provides a JavaScript polyfill for IE lower than version 9
Home-page: http://github.com/Raptus/raptus.backgroundsize
Author: Raptus AG
Author-email: dev@raptus.com
License: gpl
Platform: UNKNOWN
Classifier: Programming Language :: Python
